README.md
setup.cfg
setup.py
pvtrace/__init__.py
pvtrace.egg-info/PKG-INFO
pvtrace.egg-info/SOURCES.txt
pvtrace.egg-info/dependency_links.txt
pvtrace.egg-info/requires.txt
pvtrace.egg-info/top_level.txt
pvtrace/algorithm/__init__.py
pvtrace/algorithm/photon_tracer.py
pvtrace/common/__init__.py
pvtrace/common/errors.py
pvtrace/data/__init__.py
pvtrace/data/fluro_red.py
pvtrace/data/lumogen_f_red_305.py
pvtrace/device/__init__.py
pvtrace/device/lsc.py
pvtrace/geometry/__init__.py
pvtrace/geometry/box.py
pvtrace/geometry/cylinder.py
pvtrace/geometry/geometry.py
pvtrace/geometry/intersection.py
pvtrace/geometry/mesh.py
pvtrace/geometry/sphere.py
pvtrace/geometry/transformable.py
pvtrace/geometry/transformations.py
pvtrace/geometry/utils.py
pvtrace/light/__init__.py
pvtrace/light/event.py
pvtrace/light/light.py
pvtrace/light/ray.py
pvtrace/light/utils.py
pvtrace/material/__init__.py
pvtrace/material/component.py
pvtrace/material/distribution.py
pvtrace/material/material.py
pvtrace/material/surface.py
pvtrace/material/utils.py
pvtrace/scene/__init__.py
pvtrace/scene/node.py
pvtrace/scene/renderer.py
pvtrace/scene/scene.py
tests/__init__.py
tests/test_3D_flux_comparison.py
tests/test_box.py
tests/test_cylinder.py
tests/test_distibution.py
tests/test_frensel_reflection.py
tests/test_frensel_refraction.py
tests/test_geometry_utils.py
tests/test_intersection.py
tests/test_light_utils.py
tests/test_material.py
tests/test_mesh.py
tests/test_node.py
tests/test_refractored_tracer.py
tests/test_scene.py
tests/test_scene_renderer.py
tests/test_sphere.py
tests/test_transformable.py