Metadata-Version: 2.1
Name: pvtrace
Version: 2.1.6
Summary: Optical ray tracing for luminescent materials and spectral converter photovoltaic devices.
Home-page: https://github.com/danieljfarrell/pvtrace
Author: Daniel Farrell
Author-email: dan@excitonlabs.com
License: UNKNOWN
Download-URL: https://github.com/danieljfarrell/pvtrace/archive/2.1.6.tar.gz
Keywords: optics,raytracing,photovoltaics,energy
Platform: UNKNOWN
Classifier: Development Status :: 4 - Beta
Classifier: Intended Audience :: Science/Research
Classifier: Intended Audience :: Developers
Classifier: Topic :: Scientific/Engineering :: Physics
Classifier: Topic :: Scientific/Engineering :: Chemistry
Classifier: Topic :: Scientific/Engineering :: Visualization
Classifier: License :: OSI Approved :: BSD License
Classifier: Programming Language :: Python :: 3.7
Requires-Python: >=3.7.2,<3.8
